tumfl/Token.py
tumfl/__init__.py
tumfl/__main__.py
tumfl/basic_walker.py
tumfl/config.py
tumfl/dependency_resolver.py
tumfl/error.py
tumfl/formatter.py
tumfl/lexer.py
tumfl/parser.py
tumfl/py.typed
tumfl/semantic_analyzer.py
tumfl/to_lua_type.py
tumfl/to_python_type.py
tumfl/utils.py
tumfl/AST/__init__.py
tumfl/AST/ast_node.py
tumfl/AST/base_function_definition.py
tumfl/AST/py.typed
tumfl/AST/expression/__init__.py
tumfl/AST/expression/bin_op.py
tumfl/AST/expression/boolean.py
tumfl/AST/expression/exp_function_call.py
tumfl/AST/expression/exp_function_definition.py
tumfl/AST/expression/exp_method_invocation.py
tumfl/AST/expression/expression.py
tumfl/AST/expression/index.py
tumfl/AST/expression/name.py
tumfl/AST/expression/named_index.py
tumfl/AST/expression/nil.py
tumfl/AST/expression/number.py
tumfl/AST/expression/py.typed
tumfl/AST/expression/string.py
tumfl/AST/expression/table.py
tumfl/AST/expression/table_field.py
tumfl/AST/expression/un_op.py
tumfl/AST/expression/vararg.py
tumfl/AST/expression/variable.py
tumfl/AST/statement/__init__.py
tumfl/AST/statement/assign.py
tumfl/AST/statement/block.py
tumfl/AST/statement/break_.py
tumfl/AST/statement/chunk.py
tumfl/AST/statement/function_call.py
tumfl/AST/statement/function_definition.py
tumfl/AST/statement/goto.py
tumfl/AST/statement/if_.py
tumfl/AST/statement/iterative_for.py
tumfl/AST/statement/label.py
tumfl/AST/statement/local_assign.py
tumfl/AST/statement/local_function_definition.py
tumfl/AST/statement/method_invocation.py
tumfl/AST/statement/numeric_for.py
tumfl/AST/statement/py.typed
tumfl/AST/statement/repeat.py
tumfl/AST/statement/semicolon.py
tumfl/AST/statement/statement.py
tumfl/AST/statement/while_.py
tumfl/minifier/__init__.py
tumfl/minifier/block_optimization.py
tumfl/minifier/combine_local.py
tumfl/minifier/minify.py
tumfl/minifier/py.typed
tumfl/minifier/resolve_indexes.py
tumfl/minifier/shorten_names.py
tumfl/minifier/simplify_expressions.py
tumfl/minifier/util/__init__.py
tumfl-0.3.14.dist-info/METADATA
tumfl-0.3.14.dist-info/WHEEL
tumfl-0.3.14.dist-info/entry_points.txt
tumfl-0.3.14.dist-info/top_level.txt
tumfl-0.3.14.dist-info/RECORD
