Metadata-Version: 2.4
Name: tumfl
Version: 0.3.14
Summary: The Ultimate Minimizer For Lua: minimize your lua scripts
Author: Fabian Wunsch
License-Expression: MIT
Project-URL: homepage, https://github.com/stormworks-utils/tumfl
Project-URL: repository, https://github.com/stormworks-utils/tumfl
Keywords: lua,minimizer,ast
Classifier: Programming Language :: Python :: 3
Classifier: Development Status :: 3 - Alpha
Classifier: Intended Audience :: Developers
Classifier: Intended Audience :: Information Technology
Classifier: Operating System :: OS Independent
Classifier: Topic :: Software Development :: Libraries
Classifier: Typing :: Typed
Requires-Python: >=3.10
Requires-Dist: watchdog
Provides-Extra: dev
Requires-Dist: black; extra == "dev"
Requires-Dist: isort; extra == "dev"
Requires-Dist: pip-tools; extra == "dev"
Requires-Dist: mypy; extra == "dev"
Requires-Dist: flake8; extra == "dev"
Requires-Dist: coverage; extra == "dev"
Requires-Dist: pylint; extra == "dev"
